hjlqqq/__init__.py
hjlqqq/suhan.py
hjlqqq/__pycache__/__init__.cpython-311.pyc
hjlqqq/__pycache__/suhan.cpython-311.pyc
hjlqqq-10.5.7.dist-info/LICENSE.txt
hjlqqq-10.5.7.dist-info/METADATA
hjlqqq-10.5.7.dist-info/WHEEL
hjlqqq-10.5.7.dist-info/top_level.txt
hjlqqq-10.5.7.dist-info/RECORD
